LICENSE
MANIFEST.in
README.rst
setup.py
LD4Apps.egg-info/PKG-INFO
LD4Apps.egg-info/SOURCES.txt
LD4Apps.egg-info/dependency_links.txt
LD4Apps.egg-info/requires.txt
LD4Apps.egg-info/top_level.txt
ld4apps/__init__.py
ld4apps/aggregating_logic_tier.py
ld4apps/base_constants.py
ld4apps/cryptography.py
ld4apps/example_logic_tier.py
ld4apps/example_rdf_json_to_html_converter.py
ld4apps/lda.py
ld4apps/logic_server.py
ld4apps/rdf_json.py
ld4apps/rdfgraphlib.py
ld4apps/storage.py
ld4apps/trsbuilder.py
ld4apps/url_policy.py
ld4apps/utils.py
ld4apps/mongodbstorage/__init__.py
ld4apps/mongodbstorage/operation_primitives.py
ld4apps/mongodbstorage/storage_mapping.py
ld4apps/test/__init__.py
ld4apps/test/test_helper.py
ld4apps/test/test_utils.py