Metadata-Version: 1.0
Name: LD4Apps
Version: 0.9.7
Summary: Linked Data for Applications Server Library
Home-page: https://github.com/ld4apps/lda-serverlib/tree/ld4apps
Author: LD4Apps Team
Author-email: frankb@ca.ibm.com
License: Apache Software License
Platform: any
